pixverseai/__init__.py
pixverseai/credit.py
pixverseai/delete.py
pixverseai/extend.py
pixverseai/img_to_video3.py
pixverseai/img_to_video3_5.py
pixverseai/img_to_video4.py
pixverseai/login.py
pixverseai/personaje3_5.py
pixverseai/process.py
pixverseai/register.py
pixverseai/text_to_video4.py
pixverseai/txt_to_video3.py
pixverseai/txt_to_video3_5.py
pixverseai/up_extend.py
pixverseai/up_personaje.py
pixverseai-1.5.0.dist-info/LICENSE
pixverseai-1.5.0.dist-info/METADATA
pixverseai-1.5.0.dist-info/WHEEL
pixverseai-1.5.0.dist-info/top_level.txt
pixverseai-1.5.0.dist-info/RECORD
