Metadata-Version: 2.2
Name: pixverseai
Version: 1.5.0
Summary: esta libreria fue creada por IA Sistema de Intres
Home-page: https://www.youtube.com/@IA.Sistema.de.Interes
Author: IA (Sistema de Intres)
Author-email: system.ai.of.interest@gmail.com
Classifier: Programming Language :: Python :: 3
Classifier: License :: OSI Approved :: MIT License
Classifier: Operating System :: OS Independent
Requires-Python: >=3.6
License-File: LICENSE
Dynamic: author
Dynamic: author-email
Dynamic: classifier
Dynamic: description
Dynamic: description-content-type
Dynamic: home-page
Dynamic: requires-python
Dynamic: summary
